sjtop/__init__.py
sjtop/__main__.py
sjtop/app.py
sjtop/dashboard.py
sjtop/side.py
sjtop/status_panel.py
sjtop-0.1.2.dist-info/entry_points.txt
sjtop-0.1.2.dist-info/LICENSE
sjtop-0.1.2.dist-info/WHEEL
sjtop-0.1.2.dist-info/METADATA
sjtop-0.1.2.dist-info/RECORD
